syslog_rfc5424_parser/__init__.py
syslog_rfc5424_parser/constants.py
syslog_rfc5424_parser/message.py
syslog_rfc5424_parser/parser.py
syslog_rfc5424_parser-0.3.2.dist-info/LICENSE
syslog_rfc5424_parser-0.3.2.dist-info/METADATA
syslog_rfc5424_parser-0.3.2.dist-info/WHEEL
syslog_rfc5424_parser-0.3.2.dist-info/top_level.txt
syslog_rfc5424_parser-0.3.2.dist-info/RECORD
