Metadata-Version: 2.1
Name: syslog-rfc5424-parser
Version: 0.3.2
Summary: Parser for RFC5424-compatible Syslog messages
Home-page: https://github.com/easypost/syslog-rfc5424-parser
Author: James Brown
Author-email: jbrown@easypost.com
License: ISC
Project-URL: Issue Tracker, https://github.com/easypost/syslog-rfc5424-parser/issues
Project-URL: Documentations, https://syslog-rfc5424-parser.readthedocs.io/en/latest/
Platform: UNKNOWN
Classifier: Development Status :: 4 - Beta
Classifier: Environment :: Console
Classifier: Programming Language :: Python
Classifier: Programming Language :: Python :: 2.7
Classifier: Programming Language :: Python :: 3.4
Classifier: Programming Language :: Python :: 3.5
Classifier: Programming Language :: Python :: 3.6
Classifier: Programming Language :: Python :: 3.7
Classifier: Intended Audience :: Developers
Classifier: Operating System :: OS Independent
Classifier: License :: OSI Approved :: ISC License (ISCL)
Requires-Dist: lark-parser (==0.6.*)
